totalhuman/__init__.py
totalhuman/data/__init__.py
totalhuman/data/coco_tools.py
totalhuman/data/image.py
totalhuman/data/json_utils.py
totalhuman/eval/__init__.py
totalhuman/eval/coco.py
totalhuman/eval/mot.py
totalhuman/eval/mot_evaluator_custom.py
totalhuman/human/__init__.py
totalhuman/human/common.py
totalhuman/human/get_result.py
totalhuman/model_zoo/__init__.py
totalhuman/model_zoo/get_models.py
totalhuman/model_zoo/model_attribute/__init__.py
totalhuman/model_zoo/model_attribute/gender.py
totalhuman/model_zoo/model_common/__init__.py
totalhuman/model_zoo/model_common/load_onnx.py
totalhuman/model_zoo/model_common/load_openvino.py
totalhuman/model_zoo/model_common/load_tensorRT.py
totalhuman/model_zoo/model_common/load_tensorRT_multiple.py
totalhuman/model_zoo/model_detection/__init__.py
totalhuman/model_zoo/model_detection/yolov5.py
totalhuman/model_zoo/model_detection/yolov7.py
totalhuman/model_zoo/model_detection/yolox.py
totalhuman/model_zoo/model_pose/__init__.py
totalhuman/model_zoo/model_pose/vitpose.py
totalhuman/model_zoo/model_tracker/__init__.py
totalhuman/model_zoo/model_tracker/bytetracker.py
totalhuman/model_zoo/model_tracker/bytetrack/__init__.py
totalhuman/model_zoo/model_tracker/bytetrack/dist.py
totalhuman/model_zoo/model_tracker/bytetrack/visualize.py
totalhuman/model_zoo/model_tracker/bytetrack/tracker/__init__.py
totalhuman/model_zoo/model_tracker/bytetrack/tracker/basetrack.py
totalhuman/model_zoo/model_tracker/bytetrack/tracker/byte_tracker.py
totalhuman/model_zoo/model_tracker/bytetrack/tracker/kalman_filter.py
totalhuman/model_zoo/model_tracker/bytetrack/tracker/matching.py
totalhuman/model_zoo/model_tracker/bytetrack/tracking_utils/__init__.py
totalhuman/model_zoo/model_tracker/bytetrack/tracking_utils/io.py
totalhuman/model_zoo/model_tracker/bytetrack/tracking_utils/timer.py
totalhuman/utils/__init__.py
totalhuman/utils/utils_attribute/__init__.py
totalhuman/utils/utils_attribute/gender_util.py
totalhuman-0.0.1.dist-info/METADATA
totalhuman-0.0.1.dist-info/WHEEL
totalhuman-0.0.1.dist-info/top_level.txt
totalhuman-0.0.1.dist-info/RECORD
