Metadata-Version: 2.1
Name: totalhuman
Version: 0.0.1
Summary: totalhuman gpu package
Author: lululalamm
Author-email: yms2109@gmail.com
Requires-Python: >=3
